LICENSE
README.md
setup.py
src/speed_calculator/__init__.py
src/speed_calculator/speed_calculator.py
src/speed_calculator.egg-info/PKG-INFO
src/speed_calculator.egg-info/SOURCES.txt
src/speed_calculator.egg-info/dependency_links.txt
src/speed_calculator.egg-info/not-zip-safe
src/speed_calculator.egg-info/top_level.txt