Metadata-Version: 2.1
Name: speed-calculator
Version: 0.4.1
Summary: A library to speed calculation of a function.
Home-page: https://github.com/onuratakan/speed_calculator
Author: Onur Atakan ULUSOY
Author-email: atadogan06@gmail.com
License: MIT
Platform: UNKNOWN
Requires-Python: >= 3
